README.rst
PyVili/ArrayNode.py
PyVili/ComplexNode.py
PyVili/ContainerNode.py
PyVili/DataNode.py
PyVili/Node.py
PyVili/Types.py
PyVili/Utils.py
PyVili/ViliException.py
PyVili/ViliParser.py
PyVili/__init__.py
PyVili-1.0.3.dist-info/DESCRIPTION.rst
PyVili-1.0.3.dist-info/METADATA
PyVili-1.0.3.dist-info/RECORD
PyVili-1.0.3.dist-info/WHEEL
PyVili-1.0.3.dist-info/metadata.json
PyVili-1.0.3.dist-info/top_level.txt
