Metadata-Version: 2.0
Name: PyVili
Version: 1.0.3
Summary: PyVili is a Python API to manipulate Vili Data files
Home-page: https://github.com/Sygmei/PyVili
Author: Sygmei
Author-email: sygmei@obengine.io
License: MIT
Platform: UNKNOWN
Classifier: Development Status :: 3 - Alpha
Classifier: Intended Audience :: Developers
Classifier: License :: OSI Approved :: MIT License
Classifier: Programming Language :: Python :: 3
Classifier: Programming Language :: Python :: 3.5
